<annotation>
	<folder>train</folder>
	<filename>15.jpg</filename>
	<path>C:\GIT\object_detection_demo\data\images\train\15.jpg</path>
	<source>
		<database>Unknown</database>
	</source>
	<size>
		<width>800</width>
		<height>600</height>
		<depth>3</depth>
	</size>
	<segmented>0</segmented>
	<object>
		<name>crosswalk</name>
		<pose>Unspecified</pose>
		<truncated>0</truncated>
		<difficult>0</difficult>
		<bndbox>
			<xmin>246</xmin>
			<ymin>294</ymin>
			<xmax>524</xmax>
			<ymax>377</ymax>
		</bndbox>
	</object>
	<object>
		<name>pedestrian</name>
		<pose>Unspecified</pose>
		<truncated>0</truncated>
		<difficult>0</difficult>
		<bndbox>
			<xmin>184</xmin>
			<ymin>269</ymin>
			<xmax>221</xmax>
			<ymax>369</ymax>
		</bndbox>
	</object>
	<object>
		<name>pedestrian</name>
		<pose>Unspecified</pose>
		<truncated>0</truncated>
		<difficult>0</difficult>
		<bndbox>
			<xmin>598</xmin>
			<ymin>294</ymin>
			<xmax>647</xmax>
			<ymax>432</ymax>
		</bndbox>
	</object>
	<object>
		<name>semaphore</name>
		<pose>Unspecified</pose>
		<truncated>0</truncated>
		<difficult>0</difficult>
		<bndbox>
			<xmin>572</xmin>
			<ymin>193</ymin>
			<xmax>601</xmax>
			<ymax>264</ymax>
		</bndbox>
	</object>
	<object>
		<name>semaphore</name>
		<pose>Unspecified</pose>
		<truncated>0</truncated>
		<difficult>0</difficult>
		<bndbox>
			<xmin>299</xmin>
			<ymin>118</ymin>
			<xmax>318</xmax>
			<ymax>153</ymax>
		</bndbox>
	</object>
	<object>
		<name>pedestrian</name>
		<pose>Unspecified</pose>
		<truncated>0</truncated>
		<difficult>0</difficult>
		<bndbox>
			<xmin>531</xmin>
			<ymin>261</ymin>
			<xmax>557</xmax>
			<ymax>345</ymax>
		</bndbox>
	</object>
	<object>
		<name>pedestrian</name>
		<pose>Unspecified</pose>
		<truncated>0</truncated>
		<difficult>0</difficult>
		<bndbox>
			<xmin>252</xmin>
			<ymin>257</ymin>
			<xmax>270</xmax>
			<ymax>317</ymax>
		</bndbox>
	</object>
	<object>
		<name>crosswalk_sign</name>
		<pose>Unspecified</pose>
		<truncated>0</truncated>
		<difficult>0</difficult>
		<bndbox>
			<xmin>571</xmin>
			<ymin>137</ymin>
			<xmax>604</xmax>
			<ymax>188</ymax>
		</bndbox>
	</object>
</annotation>
